README
setup.py
ocupy/__init__.py
ocupy/bounds.py
ocupy/fixmat.py
ocupy/loader.py
ocupy/measures.py
ocupy/model.py
ocupy/parallel.py
ocupy/stimuli.py
ocupy/utils.py
ocupy/xvalidation.py
ocupy.egg-info/PKG-INFO
ocupy.egg-info/SOURCES.txt
ocupy.egg-info/dependency_links.txt
ocupy.egg-info/requires.txt
ocupy.egg-info/top_level.txt
ocupy.egg-info/zip-safe
ocupy/tests/__init__.py
ocupy/tests/test_bounds.py
ocupy/tests/test_fixmat.py
ocupy/tests/test_fixmat_compute_fdm.py
ocupy/tests/test_loader.py
ocupy/tests/test_measures.py
ocupy/tests/test_stimuli.py
ocupy/tests/test_utils.py
ocupy/tests/test_xvalidation.py