Metadata-Version: 1.0
Name: ocupy
Version: 0.1
Summary: Oculography Analysis Toolbox
Home-page: http://github.com/nwilming/ocupy/
Author: WhiteMatter Labs GmbH
Author-email: nwilming@uos.de
License: GPL v.2, see LICENSE
Platform: UNKNOWN
Classifier: Development Status :: 5 - Production/Stable
Classifier: Environment :: Console
Classifier: Intended Audience :: Science/Research
Classifier: License :: OSI Approved :: GNU General Public License (GPL)
Classifier: Operating System :: OS Independent
Classifier: Topic :: Scientific/Engineering :: Information Analysis
Classifier: Topic :: Software Development :: Libraries :: Python Modules
